appshot/__init__.py
appshot/monitor.py
appshot-0.3.dist-info/METADATA
appshot-0.3.dist-info/WHEEL
appshot-0.3.dist-info/top_level.txt
appshot-0.3.dist-info/RECORD
