Metadata-Version: 2.1
Name: appshot
Version: 0.3
Summary: ScreenShot for target window. Identy window by 1.front 2.title 3.clsname 4.hwnd. Based on win32api. Only screenshot the window not all screen and not crop.
Author-email: 2229066748@qq.com
Maintainer: Eagle'sBaby
Maintainer-email: 2229066748@qq.com
License: Apache Licence 2.0
Keywords: screenshot,utils
Platform: windows
Classifier: Programming Language :: Python
Classifier: Programming Language :: Python :: 3
Requires-Python: >=3
Requires-Dist: pywin32
